README.md
setup.py
strtobool.py
distutils_strtobool.egg-info/PKG-INFO
distutils_strtobool.egg-info/SOURCES.txt
distutils_strtobool.egg-info/dependency_links.txt
distutils_strtobool.egg-info/top_level.txt