Metadata-Version: 1.1
Name: distutils-strtobool
Version: 0.1.0
Summary: distutils.utils.strtobool
Home-page: https://github.com/yukinarit/strtobool
Author: yukinarit
Author-email: yukinarit84@gmail.com
License: Python Software Foundation License
Platform: UNKNOWN
Classifier: Development Status :: 6 - Mature
Classifier: Framework :: Robot Framework :: Library
Classifier: Intended Audience :: Developers
Classifier: License :: OSI Approved :: Python Software Foundation License
Classifier: Programming Language :: Python :: 2
Classifier: Programming Language :: Python :: 3
